aos8_api/ApiBuilder.py
aos8_api/ApiClient.py
aos8_api/__init__.py
aos8_api/exceptions.py
aos8_api/helper.py
aos8_api/models.py
aos8_api/endpoints/__init__.py
aos8_api/endpoints/base.py
aos8_api/endpoints/chassis.py
aos8_api/endpoints/cli.py
aos8_api/endpoints/interface.py
aos8_api/endpoints/ip.py
aos8_api/endpoints/lacp.py
aos8_api/endpoints/mac.py
aos8_api/endpoints/mvrp.py
aos8_api/endpoints/system.py
aos8_api/endpoints/vlan.py
aos8_api/endpoints/vpa.py
aos8_api-8.9.3.post13.dist-info/licenses/LICENSE
aos8_api-8.9.3.post13.dist-info/METADATA
aos8_api-8.9.3.post13.dist-info/WHEEL
aos8_api-8.9.3.post13.dist-info/top_level.txt
aos8_api-8.9.3.post13.dist-info/RECORD
