Metadata-Version: 2.4
Name: aos8_api
Version: 8.9.3.post13
Summary: OmniSwitch RestFUL API for Python
Author-email: Samuel Yip <kahyean.yip@gmail.com>
Requires-Python: >=3.8
License-File: LICENSE
Requires-Dist: httpx==0.28.1
Requires-Dist: dataclasses==0.6
Requires-Dist: dataclasses-json==0.6.7
Dynamic: license-file
